main.py
setting.py
api/downloader.py
api/music_player.py
api/protocols.py
api/ytmusic.py
api/mpris/mpris.py
musicterm-0.1.1.dist-info/licenses/LICENSE
player/media_control.py
player/player.py
player/util.py
musicterm-0.1.1.dist-info/METADATA
musicterm-0.1.1.dist-info/WHEEL
musicterm-0.1.1.dist-info/entry_points.txt
musicterm-0.1.1.dist-info/top_level.txt
musicterm-0.1.1.dist-info/RECORD
