Metadata-Version: 2.4
Name: MusicTerm
Version: 0.1.1
Summary: play music from your termninal.
Author-email: ZachVFX <zachallrd@gmail.com>
Project-URL: Homepage, https://github.com/ZachVFXX/PyMusicTerm
Project-URL: Issues, https://github.com/ZachVFXX/PyMusicTerm/issues
Requires-Python: >=3.12
License-File: LICENSE
Requires-Dist: just-playback>=0.1.8
Requires-Dist: msgspec>=0.19.0
Requires-Dist: pydub>=0.25.1
Requires-Dist: pytubefix>=8.12.1
Requires-Dist: textual>=1.0.0
Requires-Dist: tomli-w>=1.2.0
Requires-Dist: ytmusicapi>=1.10.1
Requires-Dist: loguru>=0.6.0
Requires-Dist: mpris-server>=0.9.0; sys_platform != "win32"
Requires-Dist: textual-image[textual]>=0.8.2
Requires-Dist: pillow>=11.1.0
Requires-Dist: music-tag>=0.4.3
Requires-Dist: requests-cache>=1.2.1
Dynamic: license-file
